cwtune/__init__.py
cwtune/analyze.py
cwtune/aws.py
cwtune/cli.py
cwtune/timeseries.py
cwtune/utils.py
cwtune-0.2.2.dist-info/LICENSE
cwtune-0.2.2.dist-info/METADATA
cwtune-0.2.2.dist-info/WHEEL
cwtune-0.2.2.dist-info/entry_points.txt
cwtune-0.2.2.dist-info/top_level.txt
cwtune-0.2.2.dist-info/RECORD
