Metadata-Version: 2.1
Name: cwtune
Version: 0.2.2
Summary: CLI for AWS CLoudWatch Alarm Tuning/Creation
Home-page: https://github.com/availabl-co/cwtune
Author: Arran McCabe
Author-email: arran@availabl.ai
License: MIT license
Keywords: cwtune
Classifier: Development Status :: 2 - Pre-Alpha
Classifier: Intended Audience :: Developers
Classifier: License :: OSI Approved :: MIT License
Classifier: Natural Language :: English
Classifier: Programming Language :: Python :: 3
Classifier: Programming Language :: Python :: 3.6
Classifier: Programming Language :: Python :: 3.7
Classifier: Programming Language :: Python :: 3.8
Requires-Python: >=3.6
License-File: LICENSE
Requires-Dist: click (>=8.1.6)
Requires-Dist: boto3 (>=1.4.0)
Requires-Dist: terminaltables (>=3.1.10)
Requires-Dist: thefuzz (>=0.19.0)
Requires-Dist: requests (>=2.18.4)
Requires-Dist: python-Levenshtein (>=0.21.1)
